MANIFEST.in
setup.py
cxapit/Authentications.so
cxapit/Tools.so
cxapit/__init__.py
cxapit.egg-info/PKG-INFO
cxapit.egg-info/SOURCES.txt
cxapit.egg-info/dependency_links.txt
cxapit.egg-info/requires.txt
cxapit.egg-info/top_level.txt
cxapit/base/tools/Common.so