Metadata-Version: 2.1
Name: cxapit
Version: 1.0.16
Summary: A Python client for the Bacalha public API
Home-page: https://github.com/bacalhau-project/bacalhau/tree/main
Author: bacalha
Author-email: xm6798121@gmail.com
License: License
Keywords: H
Platform: any
